Metadata-Version: 1.1
Name: pylef
Version: 0.1.4.3
Summary: Python module for controlling isntruments and support IFGW LEF
Home-page: https://github.com/gwiederhecker/pylef
Author: Felippe Barbosa
Author-email: felippe.barbosa@gmail.com
License: MIT v1.0
Keywords: instrument control
Platform: OS Independent
Classifier: Topic :: Scientific/Engineering :: Interface Engine/Protocol Translator
Classifier: Intended Audience :: Education
Classifier: Topic :: Education :: Computer Aided Instruction (CAI)
Provides: pylef
